mavenagi/__init__.py
mavenagi/actions/__init__.py
mavenagi/actions/client.py
mavenagi/actions/raw_client.py
mavenagi/actions/types/__init__.py
mavenagi/actions/types/action_field.py
mavenagi/actions/types/action_filter.py
mavenagi/actions/types/action_request.py
mavenagi/actions/types/actions_response.py
mavenagi/actions/types/actions_search_request.py
mavenagi/agents/__init__.py
mavenagi/agents/client.py
mavenagi/agents/raw_client.py
mavenagi/agents/types/__init__.py
mavenagi/agents/types/agent.py
mavenagi/agents/types/agent_environment.py
mavenagi/agents/types/agent_field.py
mavenagi/agents/types/agent_filter.py
mavenagi/agents/types/agent_prompting.py
mavenagi/agents/types/agents_search_request.py
mavenagi/agents/types/agents_search_response.py
mavenagi/agents/types/create_agent_request.py
mavenagi/analytics/__init__.py
mavenagi/analytics/client.py
mavenagi/analytics/raw_client.py
mavenagi/analytics/types/__init__.py
mavenagi/analytics/types/agent_user_analytics_request.py
mavenagi/analytics/types/agent_user_column_definition.py
mavenagi/analytics/types/agent_user_count.py
mavenagi/analytics/types/agent_user_metric.py
mavenagi/analytics/types/agent_user_row.py
mavenagi/analytics/types/agent_user_table_request.py
mavenagi/analytics/types/agent_user_table_response.py
mavenagi/analytics/types/bar_chart_response.py
mavenagi/analytics/types/cell_data.py
mavenagi/analytics/types/chart_response.py
mavenagi/analytics/types/column_definition_base.py
mavenagi/analytics/types/conversation_analytics_request.py
mavenagi/analytics/types/conversation_average.py
mavenagi/analytics/types/conversation_bar_chart_request.py
mavenagi/analytics/types/conversation_basic_metric.py
mavenagi/analytics/types/conversation_chart_request.py
mavenagi/analytics/types/conversation_column_definition.py
mavenagi/analytics/types/conversation_count.py
mavenagi/analytics/types/conversation_date_histogram_request.py
mavenagi/analytics/types/conversation_distinct_count.py
mavenagi-1.2.13.dist-info/METADATA
mavenagi-1.2.13.dist-info/WHEEL
mavenagi-1.2.13.dist-info/RECORD
